living_figures/__init__.py
living_figures/bio/__init__.py
living_figures/bio/epigenome/__init__.py
living_figures/bio/epigenome/test_data/download_from_ncbi.py
living_figures/bio/epigenome/utilities/__init__.py
living_figures/bio/epigenome/utilities/pacbio_file.py
living_figures/bio/epigenome/utilities/parse_rebase.py
living_figures/bio/epigenome/utilities/rebase_file.py
living_figures/bio/epigenome/widgets/__init__.py
living_figures/bio/epigenome/widgets/panepibrowser.py
living_figures/bio/fom/__init__.py
living_figures/bio/fom/utilities/__init__.py
living_figures/bio/fom/utilities/parse_tax_string.py
living_figures/bio/fom/utilities/parse_taxon_abundances.py
living_figures/bio/fom/widgets/microbiome/__init__.py
living_figures/bio/fom/widgets/microbiome/abundant_orgs.py
living_figures/bio/fom/widgets/microbiome/alpha_diversity.py
living_figures/bio/fom/widgets/microbiome/base_plots.py
living_figures/bio/fom/widgets/microbiome/base_widget.py
living_figures/bio/fom/widgets/microbiome/beta_diversity.py
living_figures/bio/fom/widgets/microbiome/differential_abundance.py
living_figures/bio/fom/widgets/microbiome/inputs.py
living_figures/bio/fom/widgets/microbiome/main.py
living_figures/bio/fom/widgets/microbiome/ordination.py
living_figures/bio/volcano/__init__.py
living_figures/bio/volcano/app.py
living_figures/bio/volcano/make_test_data.py
living_figures/helpers/__init__.py
living_figures/helpers/constants.py
living_figures/helpers/parse_numeric.py
living_figures/helpers/scaling.py
living_figures/helpers/sorting.py
living_figures-0.2.0.dist-info/LICENSE
living_figures-0.2.0.dist-info/METADATA
living_figures-0.2.0.dist-info/WHEEL
living_figures-0.2.0.dist-info/top_level.txt
living_figures-0.2.0.dist-info/RECORD
