Metadata-Version: 2.1
Name: living-figures
Version: 0.2.0
Summary: Resource of interactive data widgets
Author-email: Samuel Minot <sminot@fredhutch.org>
Project-URL: Homepage, https://github.com/FredHutch/widgets-store
Project-URL: Bug Tracker, https://github.com/FredHutch/widgets-store/issues
Classifier: Programming Language :: Python :: 3
Classifier: License :: OSI Approved :: MIT License
Classifier: Operating System :: OS Independent
Requires-Python: >=3.7
License-File: LICENSE
Requires-Dist: widgets-lib (>=2.6.0)
Requires-Dist: plotly
Requires-Dist: pandas
Requires-Dist: scipy
Requires-Dist: scikit-learn
